chrombpnet/CHROMBPNET.py
chrombpnet/__init__.py
chrombpnet/parsers.py
chrombpnet/pipelines.py
chrombpnet/data/ATAC.ref.motifs.txt
chrombpnet/data/DNASE.ref.motifs.txt
chrombpnet/data/__init__.py
chrombpnet/data/motif_to_pwm.ATAC.tsv
chrombpnet/data/motif_to_pwm.DNASE.tsv
chrombpnet/data/motif_to_pwm.TF.tsv
chrombpnet/data/motifs.meme.txt
chrombpnet/evaluation/__init__.py
chrombpnet/evaluation/interpret/__init__.py
chrombpnet/evaluation/interpret/input_utils.py
chrombpnet/evaluation/interpret/interpret.py
chrombpnet/evaluation/interpret/shap_utils.py
chrombpnet/evaluation/invivo_footprints/__init__.py
chrombpnet/evaluation/invivo_footprints/run_tfmodisco.py
chrombpnet/evaluation/invivo_footprints/tf_modiscohits.py
chrombpnet/evaluation/make_bigwigs/__init__.py
chrombpnet/evaluation/make_bigwigs/bigwig_helper.py
chrombpnet/evaluation/make_bigwigs/importance_hdf5_to_bigwig.py
chrombpnet/evaluation/make_bigwigs/predict_to_bigwig.py
chrombpnet/evaluation/marginal_footprints/__init__.py
chrombpnet/evaluation/marginal_footprints/marginal_footprinting.py
chrombpnet/evaluation/modisco/__init__.py
chrombpnet/evaluation/modisco/convert_html_to_pdf.py
chrombpnet/evaluation/modisco/fetch_tomtom.py
chrombpnet/evaluation/modisco/run_modisco.py
chrombpnet/evaluation/modisco/visualize_motif_matches.py
chrombpnet/evaluation/variant_effect_prediction/__init__.py
chrombpnet/evaluation/variant_effect_prediction/snp_generator.py
chrombpnet/evaluation/variant_effect_prediction/snp_scoring.py
chrombpnet/evaluation/variant_effect_prediction/testing.py
chrombpnet/helpers/__init__.py
chrombpnet/helpers/generate_reports/__init__.py
chrombpnet/helpers/generate_reports/make_html.py
chrombpnet/helpers/generate_reports/make_html_bias.py
chrombpnet/helpers/hyperparameters/__init__.py
chrombpnet/helpers/hyperparameters/find_bias_hyperparams.py
chrombpnet/helpers/hyperparameters/find_chrombpnet_hyperparams.py
chrombpnet/helpers/hyperparameters/param_utils.py
chrombpnet-0.1.7.dist-info/LICENSE
chrombpnet-0.1.7.dist-info/METADATA
chrombpnet-0.1.7.dist-info/WHEEL
chrombpnet-0.1.7.dist-info/entry_points.txt
chrombpnet-0.1.7.dist-info/top_level.txt
chrombpnet-0.1.7.dist-info/RECORD
