Metadata-Version: 2.1
Name: chrombpnet
Version: 0.1.7
Summary: chrombpnet predicts chromatin accessibility from sequence
Download-URL: https://github.com/kundajelab/chrombpnet
Author-email: anusri @ stanford.edu
License: MIT
Requires-Python: >=3.8
License-File: LICENSE
Requires-Dist: h5py >=2.10.0
Requires-Dist: matplotlib >=3.3.1
Requires-Dist: matplotlib-venn ==0.11.6
Requires-Dist: numpy ==1.23.4
Requires-Dist: pandas >=1.3.4
Requires-Dist: pyfaidx ==0.6.1
Requires-Dist: scikit-learn >=1.1.2
Requires-Dist: scipy >=1.4.1
Requires-Dist: tensorflow ==2.8.0
Requires-Dist: tensorflow-estimator ==2.8.0
Requires-Dist: tensorflow-probability ==0.15.0
Requires-Dist: protobuf ==3.20
Requires-Dist: tqdm ==4.48.2
Requires-Dist: deepdish ==0.3.7
Requires-Dist: deeplift ==0.6.13.0
Requires-Dist: modisco ==0.5.16.0
Requires-Dist: modisco-lite ==2.0.7
Requires-Dist: weasyprint ==52.5
Requires-Dist: kundajelab-shap ==1
